google_drive_helper/__init__.py
google_drive_helper/google_drive_deleter.py
google_drive_helper/google_drive_explorer.py
google_drive_helper/google_drive_uploader.py
google_drive_helper/src/auth.py
google_drive_helper/src/drive_manager.py
google_drive_helper/src/file_deleter.py
google_drive_helper/src/file_uploader.py
bdd_google_drive_helper-0.1.1.dist-info/METADATA
bdd_google_drive_helper-0.1.1.dist-info/WHEEL
bdd_google_drive_helper-0.1.1.dist-info/RECORD
