Metadata-Version: 2.1
Name: bdd-google-drive-helper
Version: 0.1.1
Summary: A simple Google Drive file uploader tool.
License: MIT
Author: Ray Lu
Author-email: raylu@gamania.com
Requires-Python: >=3.9,<4.0
Classifier: License :: OSI Approved :: MIT License
Classifier: Programming Language :: Python :: 3
Classifier: Programming Language :: Python :: 3.9
Classifier: Programming Language :: Python :: 3.10
Classifier: Programming Language :: Python :: 3.11
Classifier: Programming Language :: Python :: 3.12
Requires-Dist: google-api-python-client (>=2.142.0,<3.0.0)
Requires-Dist: google-auth (>=2.34.0,<3.0.0)
Requires-Dist: google-auth-httplib2 (>=0.2.0,<0.3.0)
Requires-Dist: google-auth-oauthlib (>=1.2.1,<2.0.0)
Requires-Dist: httplib2 (>=0.22.0,<0.23.0)
